muse/__init__.py
multi_slit_solar_explorer-0.0.3.dist-info/METADATA
multi_slit_solar_explorer-0.0.3.dist-info/WHEEL
multi_slit_solar_explorer-0.0.3.dist-info/top_level.txt
multi_slit_solar_explorer-0.0.3.dist-info/RECORD
