Metadata-Version: 2.1
Name: multi-slit-solar-explorer
Version: 0.0.3
Summary: A model of the optical design for the Multi-slit Solar Explorer (MUSE).
Author-email: "Jacob D. Parker" <jacobdparker@gmail.com>, "Roy T. Smart" <roytsmart@gmail.com>
Project-URL: Homepage, https://github.com/sun-data/multi-slit-solar-explorer
Project-URL: Documentation, https://sun-data-multi-slit-solar-explorer.readthedocs-hosted.com
Classifier: Programming Language :: Python :: 3
Requires-Python: >=3.10
Requires-Dist: astropy
Requires-Dist: optika ==0.5.0
Provides-Extra: doc
Requires-Dist: pytest ; extra == 'doc'
Requires-Dist: matplotlib ; extra == 'doc'
Requires-Dist: graphviz ; extra == 'doc'
Requires-Dist: sphinx-autodoc-typehints ; extra == 'doc'
Requires-Dist: sphinxcontrib-bibtex ; extra == 'doc'
Requires-Dist: pydata-sphinx-theme ; extra == 'doc'
Requires-Dist: ipykernel ; extra == 'doc'
Requires-Dist: jupyter-sphinx ; extra == 'doc'
Requires-Dist: sphinx-favicon ; extra == 'doc'
Provides-Extra: test
Requires-Dist: pytest ; extra == 'test'
